Metadata-Version: 1.1
Name: mvcbotbase
Version: 0.1
Summary: A base to make social network bots (generic)
Home-page: https://github.com/megahomyak/mvcbotbase
Author: megahomyak
Author-email: g.megahomyak@gmail.com
License: UNKNOWN
Download-URL: https://github.com/megahomyak/mvcbotbase/archive/v0.1.tar.gz
Platform: UNKNOWN
